Metadata-Version: 1.2
Name: python-magic-pure
Version: 0.1.0
Summary: Pure python replacement for python-magic.
Home-page: https://github.com/jkapelner/python-magic-pure
Author: Jordan Kapelner
Author-email: 
License: MIT
Platform: UNKNOWN
Classifier: Programming Language :: Python
Classifier: Programming Language :: Python :: 3
Classifier: Programming Language :: Python :: Implementation :: PyPy
Classifier: Development Status :: 5 - Production/Stable
Classifier: Natural Language :: English
Classifier: Intended Audience :: Developers
Classifier: License :: OSI Approved :: MIT License
Classifier: Operating System :: OS Independent
Classifier: Topic :: Utilities
Requires-Python: >=3.7
